{"bubenga":{"city":"Bubenga","count":"0","id":"6038413","url":"https://www.booking.com/searchresults.en.html?city=6038413&aid=8061748&no_rooms=1&group_adults=2"},"bujumbura":{"city":"Bujumbura","count":"36","id":"6034170","url":"https://www.booking.com/searchresults.en.html?city=6034170&aid=8061748&no_rooms=1&group_adults=2"},"gasarara":{"city":"Gasarara","count":"0","id":"6034058","url":"https://www.booking.com/searchresults.en.html?city=6034058&aid=8061748&no_rooms=1&group_adults=2"},"gatumba":{"city":"Gatumba","count":"0","id":"6033962","url":"https://www.booking.com/searchresults.en.html?city=6033962&aid=8061748&no_rooms=1&group_adults=2"},"gitega":{"city":"Gitega","count":"0","id":"6037737","url":"https://www.booking.com/searchresults.en.html?city=6037737&aid=8061748&no_rooms=1&group_adults=2"},"kibonangona":{"city":"Kibonangona","count":"0","id":"6035555","url":"https://www.booking.com/searchresults.en.html?city=6035555&aid=8061748&no_rooms=1&group_adults=2"},"kobero":{"city":"Kobero","count":"1","id":"6040151","url":"https://www.booking.com/searchresults.en.html?city=6040151&aid=8061748&no_rooms=1&group_adults=2"},"makamba":{"city":"Makamba","count":"0","id":"6030885","url":"https://www.booking.com/searchresults.en.html?city=6030885&aid=8061748&no_rooms=1&group_adults=2"},"mugotora":{"city":"Mugotora","count":"1","id":"6032146","url":"https://www.booking.com/searchresults.en.html?city=6032146&aid=8061748&no_rooms=1&group_adults=2"},"musaga":{"city":"Musaga","count":"1","id":"6034075","url":"https://www.booking.com/searchresults.en.html?city=6034075&aid=8061748&no_rooms=1&group_adults=2"},"mutumba":{"city":"Mutumba","count":"1","id":"6032308","url":"https://www.booking.com/searchresults.en.html?city=6032308&aid=8061748&no_rooms=1&group_adults=2"},"ngozi":{"city":"Ngozi","count":"0","id":"6039222","url":"https://www.booking.com/searchresults.en.html?city=6039222&aid=8061748&no_rooms=1&group_adults=2"},"nyakabiga":{"city":"Nyakabiga","count":"0","id":"6034014","url":"https://www.booking.com/searchresults.en.html?city=6034014&aid=8061748&no_rooms=1&group_adults=2"},"rohero":{"city":"Rohero","count":"0","id":"6034027","url":"https://www.booking.com/searchresults.en.html?city=6034027&aid=8061748&no_rooms=1&group_adults=2"},"runzenze":{"city":"Runzenze","count":"0","id":"6039890","url":"https://www.booking.com/searchresults.en.html?city=6039890&aid=8061748&no_rooms=1&group_adults=2"},"rutana":{"city":"Rutana","count":"1","id":"6066239","url":"https://www.booking.com/searchresults.en.html?city=6066239&aid=8061748&no_rooms=1&group_adults=2"},"taba":{"city":"Taba","count":"0","id":"6036701","url":"https://www.booking.com/searchresults.en.html?city=6036701&aid=8061748&no_rooms=1&group_adults=2"},"usumbura":{"city":"Usumbura","count":"0","id":"6034031","url":"https://www.booking.com/searchresults.en.html?city=6034031&aid=8061748&no_rooms=1&group_adults=2"}}