{"beachcomber island":{"city":"Beachcomber Island","count":"1","id":"900050929","url":"https://www.booking.com/searchresults.en.html?city=900050929&aid=8061748&no_rooms=1&group_adults=2"},"beqa island":{"city":"Beqa Island","count":"2","id":"900051483","url":"https://www.booking.com/searchresults.en.html?city=900051483&aid=8061748&no_rooms=1&group_adults=2"},"castaway island":{"city":"Castaway Island","count":"1","id":"900050661","url":"https://www.booking.com/searchresults.en.html?city=900050661&aid=8061748&no_rooms=1&group_adults=2"},"denarau":{"city":"Denarau","count":"9","id":"900050913","url":"https://www.booking.com/searchresults.en.html?city=900050913&aid=8061748&no_rooms=1&group_adults=2"},"drawaqa island":{"city":"Drawaqa Island","count":"1","id":"900060892","url":"https://www.booking.com/searchresults.en.html?city=900060892&aid=8061748&no_rooms=1&group_adults=2"},"kadavu":{"city":"Kadavu","count":"1","id":"900053798","url":"https://www.booking.com/searchresults.en.html?city=900053798&aid=8061748&no_rooms=1&group_adults=2"},"kandavu":{"city":"Kandavu","count":"1","id":"-1187896","url":"https://www.booking.com/searchresults.en.html?city=-1187896&aid=8061748&no_rooms=1&group_adults=2"},"kandavu island":{"city":"Kandavu Island","count":"0","id":"900052272","url":"https://www.booking.com/searchresults.en.html?city=900052272&aid=8061748&no_rooms=1&group_adults=2"},"komave":{"city":"Komave","count":"0","id":"-1188043","url":"https://www.booking.com/searchresults.en.html?city=-1188043&aid=8061748&no_rooms=1&group_adults=2"},"koroiyatha":{"city":"Koroiyatha","count":"4","id":"-1188122","url":"https://www.booking.com/searchresults.en.html?city=-1188122&aid=8061748&no_rooms=1&group_adults=2"},"korolevu":{"city":"Korolevu","count":"5","id":"900048244","url":"https://www.booking.com/searchresults.en.html?city=900048244&aid=8061748&no_rooms=1&group_adults=2"},"korotogo":{"city":"Korotogo","count":"4","id":"-1188311","url":"https://www.booking.com/searchresults.en.html?city=-1188311&aid=8061748&no_rooms=1&group_adults=2"},"korovou":{"city":"Korovou","count":"1","id":"-1188354","url":"https://www.booking.com/searchresults.en.html?city=-1188354&aid=8061748&no_rooms=1&group_adults=2"},"kuata":{"city":"Kuata","count":"1","id":"900052504","url":"https://www.booking.com/searchresults.en.html?city=900052504&aid=8061748&no_rooms=1&group_adults=2"},"labasa":{"city":"Labasa","count":"5","id":"-1188456","url":"https://www.booking.com/searchresults.en.html?city=-1188456&aid=8061748&no_rooms=1&group_adults=2"},"lalati":{"city":"Lalati","count":"1","id":"-1188450","url":"https://www.booking.com/searchresults.en.html?city=-1188450&aid=8061748&no_rooms=1&group_adults=2"},"lami":{"city":"Lami","count":"0","id":"-1188463","url":"https://www.booking.com/searchresults.en.html?city=-1188463&aid=8061748&no_rooms=1&group_adults=2"},"lauthala bay":{"city":"Lauthala Bay","count":"0","id":"-1188537","url":"https://www.booking.com/searchresults.en.html?city=-1188537&aid=8061748&no_rooms=1&group_adults=2"},"lautoka":{"city":"Lautoka","count":"21","id":"-1188543","url":"https://www.booking.com/searchresults.en.html?city=-1188543&aid=8061748&no_rooms=1&group_adults=2"},"lauwaki":{"city":"Lauwaki","count":"0","id":"-1188544","url":"https://www.booking.com/searchresults.en.html?city=-1188544&aid=8061748&no_rooms=1&group_adults=2"},"lawaki":{"city":"Lawaki","count":"0","id":"-1188565","url":"https://www.booking.com/searchresults.en.html?city=-1188565&aid=8061748&no_rooms=1&group_adults=2"},"lawangga":{"city":"Lawangga","count":"0","id":"-1188584","url":"https://www.booking.com/searchresults.en.html?city=-1188584&aid=8061748&no_rooms=1&group_adults=2"},"levuka":{"city":"Levuka","count":"0","id":"-1188635","url":"https://www.booking.com/searchresults.en.html?city=-1188635&aid=8061748&no_rooms=1&group_adults=2"},"lovonivonu":{"city":"Lovonivonu","count":"0","id":"-1188825","url":"https://www.booking.com/searchresults.en.html?city=-1188825&aid=8061748&no_rooms=1&group_adults=2"},"malakati":{"city":"Malakati","count":"0","id":"-1188904","url":"https://www.booking.com/searchresults.en.html?city=-1188904&aid=8061748&no_rooms=1&group_adults=2"},"malake":{"city":"Malake","count":"0","id":"-1188907","url":"https://www.booking.com/searchresults.en.html?city=-1188907&aid=8061748&no_rooms=1&group_adults=2"},"malolo":{"city":"Malolo","count":"6","id":"900048679","url":"https://www.booking.com/searchresults.en.html?city=900048679&aid=8061748&no_rooms=1&group_adults=2"},"malolo lailai":{"city":"Malolo Lailai","count":"9","id":"900048693","url":"https://www.booking.com/searchresults.en.html?city=900048693&aid=8061748&no_rooms=1&group_adults=2"},"mamanuca islands":{"city":"Mamanuca Islands","count":"1","id":"900060908","url":"https://www.booking.com/searchresults.en.html?city=900060908&aid=8061748&no_rooms=1&group_adults=2"},"mana island":{"city":"Mana Island","count":"4","id":"900050476","url":"https://www.booking.com/searchresults.en.html?city=900050476&aid=8061748&no_rooms=1&group_adults=2"},"matacawalevu":{"city":"Matacawalevu","count":"0","id":"900052623","url":"https://www.booking.com/searchresults.en.html?city=900052623&aid=8061748&no_rooms=1&group_adults=2"},"matamanoa island":{"city":"Matamanoa Island","count":"1","id":"900051491","url":"https://www.booking.com/searchresults.en.html?city=900051491&aid=8061748&no_rooms=1&group_adults=2"},"matangi island":{"city":"Matangi Island","count":"1","id":"900054057","url":"https://www.booking.com/searchresults.en.html?city=900054057&aid=8061748&no_rooms=1&group_adults=2"},"matayalevu":{"city":"Matayalevu","count":"1","id":"-1189186","url":"https://www.booking.com/searchresults.en.html?city=-1189186&aid=8061748&no_rooms=1&group_adults=2"},"matei":{"city":"Matei","count":"10","id":"900050456","url":"https://www.booking.com/searchresults.en.html?city=900050456&aid=8061748&no_rooms=1&group_adults=2"},"mavua":{"city":"Mavua","count":"0","id":"-1189229","url":"https://www.booking.com/searchresults.en.html?city=-1189229&aid=8061748&no_rooms=1&group_adults=2"},"mbatiri":{"city":"Mbatiri","count":"0","id":"-1189316","url":"https://www.booking.com/searchresults.en.html?city=-1189316&aid=8061748&no_rooms=1&group_adults=2"},"mbavu":{"city":"Mbavu","count":"0","id":"-1189335","url":"https://www.booking.com/searchresults.en.html?city=-1189335&aid=8061748&no_rooms=1&group_adults=2"},"mbukama":{"city":"Mbukama","count":"1","id":"-1189444","url":"https://www.booking.com/searchresults.en.html?city=-1189444&aid=8061748&no_rooms=1&group_adults=2"},"mbukuya":{"city":"Mbukuya","count":"0","id":"-1189451","url":"https://www.booking.com/searchresults.en.html?city=-1189451&aid=8061748&no_rooms=1&group_adults=2"},"melimeli":{"city":"Melimeli","count":"0","id":"-1189563","url":"https://www.booking.com/searchresults.en.html?city=-1189563&aid=8061748&no_rooms=1&group_adults=2"},"momi":{"city":"Momi","count":"1","id":"-1189610","url":"https://www.booking.com/searchresults.en.html?city=-1189610&aid=8061748&no_rooms=1&group_adults=2"},"nabila":{"city":"Nabila","count":"1","id":"-1190701","url":"https://www.booking.com/searchresults.en.html?city=-1190701&aid=8061748&no_rooms=1&group_adults=2"},"nacula island":{"city":"Nacula Island","count":"6","id":"900054446","url":"https://www.booking.com/searchresults.en.html?city=900054446&aid=8061748&no_rooms=1&group_adults=2"},"nadi":{"city":"Nadi","count":"84","id":"-1191076","url":"https://www.booking.com/searchresults.en.html?city=-1191076&aid=8061748&no_rooms=1&group_adults=2"},"naevuevu":{"city":"Naevuevu","count":"0","id":"-1189764","url":"https://www.booking.com/searchresults.en.html?city=-1189764&aid=8061748&no_rooms=1&group_adults=2"},"naindi":{"city":"Naindi","count":"0","id":"-1189861","url":"https://www.booking.com/searchresults.en.html?city=-1189861&aid=8061748&no_rooms=1&group_adults=2"},"naingani":{"city":"Naingani","count":"0","id":"-1189873","url":"https://www.booking.com/searchresults.en.html?city=-1189873&aid=8061748&no_rooms=1&group_adults=2"},"naisisili":{"city":"Naisisili","count":"0","id":"900050323","url":"https://www.booking.com/searchresults.en.html?city=900050323&aid=8061748&no_rooms=1&group_adults=2"},"nakavu":{"city":"Nakavu","count":"4","id":"-1190199","url":"https://www.booking.com/searchresults.en.html?city=-1190199&aid=8061748&no_rooms=1&group_adults=2"},"nakorokula":{"city":"Nakorokula","count":"0","id":"-1190269","url":"https://www.booking.com/searchresults.en.html?city=-1190269&aid=8061748&no_rooms=1&group_adults=2"},"nalauwaki":{"city":"Nalauwaki","count":"1","id":"-1190366","url":"https://www.booking.com/searchresults.en.html?city=-1190366&aid=8061748&no_rooms=1&group_adults=2"},"namanggumanggua":{"city":"Namanggumanggua","count":"1","id":"-1190506","url":"https://www.booking.com/searchresults.en.html?city=-1190506&aid=8061748&no_rooms=1&group_adults=2"},"namara":{"city":"Namara","count":"0","id":"-1190512","url":"https://www.booking.com/searchresults.en.html?city=-1190512&aid=8061748&no_rooms=1&group_adults=2"},"namatakula":{"city":"Namatakula","count":"2","id":"-1190554","url":"https://www.booking.com/searchresults.en.html?city=-1190554&aid=8061748&no_rooms=1&group_adults=2"},"namboutini":{"city":"Namboutini","count":"0","id":"-1190774","url":"https://www.booking.com/searchresults.en.html?city=-1190774&aid=8061748&no_rooms=1&group_adults=2"},"nanuya balavu island":{"city":"Nanuya Balavu Island","count":"1","id":"900049736","url":"https://www.booking.com/searchresults.en.html?city=900049736&aid=8061748&no_rooms=1&group_adults=2"},"nanuya lailai":{"city":"Nanuya Lailai","count":"4","id":"900056257","url":"https://www.booking.com/searchresults.en.html?city=900056257&aid=8061748&no_rooms=1&group_adults=2"},"nasekula":{"city":"Nasekula","count":"0","id":"-1191771","url":"https://www.booking.com/searchresults.en.html?city=-1191771&aid=8061748&no_rooms=1&group_adults=2"},"nasinu":{"city":"Nasinu","count":"0","id":"-1191841","url":"https://www.booking.com/searchresults.en.html?city=-1191841&aid=8061748&no_rooms=1&group_adults=2"},"natadola":{"city":"Natadola","count":"4","id":"900051475","url":"https://www.booking.com/searchresults.en.html?city=900051475&aid=8061748&no_rooms=1&group_adults=2"},"nathavanandi":{"city":"Nathavanandi","count":"0","id":"-1192083","url":"https://www.booking.com/searchresults.en.html?city=-1192083&aid=8061748&no_rooms=1&group_adults=2"},"nathekoro":{"city":"Nathekoro","count":"0","id":"-1192097","url":"https://www.booking.com/searchresults.en.html?city=-1192097&aid=8061748&no_rooms=1&group_adults=2"},"nathovu":{"city":"Nathovu","count":"1","id":"-1192139","url":"https://www.booking.com/searchresults.en.html?city=-1192139&aid=8061748&no_rooms=1&group_adults=2"},"nathula":{"city":"Nathula","count":"0","id":"-1192145","url":"https://www.booking.com/searchresults.en.html?city=-1192145&aid=8061748&no_rooms=1&group_adults=2"},"natunuku":{"city":"Natunuku","count":"0","id":"-1192280","url":"https://www.booking.com/searchresults.en.html?city=-1192280&aid=8061748&no_rooms=1&group_adults=2"},"natuvu":{"city":"Natuvu","count":"0","id":"-1192310","url":"https://www.booking.com/searchresults.en.html?city=-1192310&aid=8061748&no_rooms=1&group_adults=2"},"naukacuvu island":{"city":"Naukacuvu Island","count":"1","id":"900051501","url":"https://www.booking.com/searchresults.en.html?city=900051501&aid=8061748&no_rooms=1&group_adults=2"},"nausori":{"city":"Nausori","count":"3","id":"-1192349","url":"https://www.booking.com/searchresults.en.html?city=-1192349&aid=8061748&no_rooms=1&group_adults=2"},"navala":{"city":"Navala","count":"2","id":"-1192437","url":"https://www.booking.com/searchresults.en.html?city=-1192437&aid=8061748&no_rooms=1&group_adults=2"},"navata":{"city":"Navata","count":"0","id":"-1192468","url":"https://www.booking.com/searchresults.en.html?city=-1192468&aid=8061748&no_rooms=1&group_adults=2"},"navatu":{"city":"Navatu","count":"0","id":"-1192478","url":"https://www.booking.com/searchresults.en.html?city=-1192478&aid=8061748&no_rooms=1&group_adults=2"},"naviti island":{"city":"Naviti Island","count":"0","id":"900052705","url":"https://www.booking.com/searchresults.en.html?city=900052705&aid=8061748&no_rooms=1&group_adults=2"},"navotua":{"city":"Navotua","count":"0","id":"-1192695","url":"https://www.booking.com/searchresults.en.html?city=-1192695&aid=8061748&no_rooms=1&group_adults=2"},"navuatu":{"city":"Navuatu","count":"0","id":"-1192717","url":"https://www.booking.com/searchresults.en.html?city=-1192717&aid=8061748&no_rooms=1&group_adults=2"},"navunikambi":{"city":"Navunikambi","count":"1","id":"-1192766","url":"https://www.booking.com/searchresults.en.html?city=-1192766&aid=8061748&no_rooms=1&group_adults=2"},"nawaka":{"city":"Nawaka","count":"0","id":"-1192925","url":"https://www.booking.com/searchresults.en.html?city=-1192925&aid=8061748&no_rooms=1&group_adults=2"},"naweni":{"city":"Naweni","count":"0","id":"-1192992","url":"https://www.booking.com/searchresults.en.html?city=-1192992&aid=8061748&no_rooms=1&group_adults=2"},"nawi":{"city":"Nawi","count":"3","id":"-1192996","url":"https://www.booking.com/searchresults.en.html?city=-1192996&aid=8061748&no_rooms=1&group_adults=2"},"ndreketi":{"city":"Ndreketi","count":"0","id":"-1193489","url":"https://www.booking.com/searchresults.en.html?city=-1193489&aid=8061748&no_rooms=1&group_adults=2"},"ngunu":{"city":"Ngunu","count":"0","id":"-1193878","url":"https://www.booking.com/searchresults.en.html?city=-1193878&aid=8061748&no_rooms=1&group_adults=2"},"nukubati":{"city":"Nukubati","count":"1","id":"900055813","url":"https://www.booking.com/searchresults.en.html?city=900055813&aid=8061748&no_rooms=1&group_adults=2"},"ono island":{"city":"Ono Island","count":"1","id":"900051476","url":"https://www.booking.com/searchresults.en.html?city=900051476&aid=8061748&no_rooms=1&group_adults=2"},"pacific harbour":{"city":"Pacific Harbour","count":"8","id":"900048076","url":"https://www.booking.com/searchresults.en.html?city=900048076&aid=8061748&no_rooms=1&group_adults=2"},"qamea":{"city":"Qamea","count":"2","id":"900051473","url":"https://www.booking.com/searchresults.en.html?city=900051473&aid=8061748&no_rooms=1&group_adults=2"},"rakiraki":{"city":"Rakiraki","count":"8","id":"-1194285","url":"https://www.booking.com/searchresults.en.html?city=-1194285&aid=8061748&no_rooms=1&group_adults=2"},"rewasau":{"city":"Rewasau","count":"0","id":"-1194391","url":"https://www.booking.com/searchresults.en.html?city=-1194391&aid=8061748&no_rooms=1&group_adults=2"},"salialevu":{"city":"Salialevu","count":"0","id":"-1194495","url":"https://www.booking.com/searchresults.en.html?city=-1194495&aid=8061748&no_rooms=1&group_adults=2"},"sanasana":{"city":"Sanasana","count":"0","id":"-1194530","url":"https://www.booking.com/searchresults.en.html?city=-1194530&aid=8061748&no_rooms=1&group_adults=2"},"sarava":{"city":"Sarava","count":"0","id":"-1194559","url":"https://www.booking.com/searchresults.en.html?city=-1194559&aid=8061748&no_rooms=1&group_adults=2"},"savusavu":{"city":"Savusavu","count":"25","id":"-1194746","url":"https://www.booking.com/searchresults.en.html?city=-1194746&aid=8061748&no_rooms=1&group_adults=2"},"serua":{"city":"Serua","count":"0","id":"-1194854","url":"https://www.booking.com/searchresults.en.html?city=-1194854&aid=8061748&no_rooms=1&group_adults=2"},"sigatoka":{"city":"Sigatoka","count":"11","id":"-1194905","url":"https://www.booking.com/searchresults.en.html?city=-1194905&aid=8061748&no_rooms=1&group_adults=2"},"solevu":{"city":"Solevu","count":"0","id":"-1194945","url":"https://www.booking.com/searchresults.en.html?city=-1194945&aid=8061748&no_rooms=1&group_adults=2"},"suva":{"city":"Suva","count":"54","id":"-1195133","url":"https://www.booking.com/searchresults.en.html?city=-1195133&aid=8061748&no_rooms=1&group_adults=2"},"tangangge":{"city":"Tangangge","count":"8","id":"-1195265","url":"https://www.booking.com/searchresults.en.html?city=-1195265&aid=8061748&no_rooms=1&group_adults=2"},"tavewa":{"city":"Tavewa","count":"2","id":"900050269","url":"https://www.booking.com/searchresults.en.html?city=900050269&aid=8061748&no_rooms=1&group_adults=2"},"tavua":{"city":"Tavua","count":"0","id":"-1195400","url":"https://www.booking.com/searchresults.en.html?city=-1195400&aid=8061748&no_rooms=1&group_adults=2"},"tavuki":{"city":"Tavuki","count":"0","id":"-1195411","url":"https://www.booking.com/searchresults.en.html?city=-1195411&aid=8061748&no_rooms=1&group_adults=2"},"tethi":{"city":"Tethi","count":"0","id":"-1195469","url":"https://www.booking.com/searchresults.en.html?city=-1195469&aid=8061748&no_rooms=1&group_adults=2"},"the domain":{"city":"The Domain","count":"0","id":"-1195538","url":"https://www.booking.com/searchresults.en.html?city=-1195538&aid=8061748&no_rooms=1&group_adults=2"},"thuvu":{"city":"Thuvu","count":"1","id":"-1195625","url":"https://www.booking.com/searchresults.en.html?city=-1195625&aid=8061748&no_rooms=1&group_adults=2"},"tiliva":{"city":"Tiliva","count":"0","id":"-1195644","url":"https://www.booking.com/searchresults.en.html?city=-1195644&aid=8061748&no_rooms=1&group_adults=2"},"toberua":{"city":"Toberua","count":"1","id":"900050214","url":"https://www.booking.com/searchresults.en.html?city=900050214&aid=8061748&no_rooms=1&group_adults=2"},"tokoriki":{"city":"Tokoriki","count":"2","id":"900050322","url":"https://www.booking.com/searchresults.en.html?city=900050322&aid=8061748&no_rooms=1&group_adults=2"},"tonge":{"city":"Tonge","count":"0","id":"-1195748","url":"https://www.booking.com/searchresults.en.html?city=-1195748&aid=8061748&no_rooms=1&group_adults=2"},"toorak":{"city":"Toorak","count":"1","id":"-1195766","url":"https://www.booking.com/searchresults.en.html?city=-1195766&aid=8061748&no_rooms=1&group_adults=2"},"totongo":{"city":"Totongo","count":"0","id":"-1195778","url":"https://www.booking.com/searchresults.en.html?city=-1195778&aid=8061748&no_rooms=1&group_adults=2"},"treasure island":{"city":"Treasure Island","count":"1","id":"900050477","url":"https://www.booking.com/searchresults.en.html?city=900050477&aid=8061748&no_rooms=1&group_adults=2"},"urata":{"city":"Urata","count":"0","id":"-1196014","url":"https://www.booking.com/searchresults.en.html?city=-1196014&aid=8061748&no_rooms=1&group_adults=2"},"vathaleya":{"city":"Vathaleya","count":"0","id":"-1196260","url":"https://www.booking.com/searchresults.en.html?city=-1196260&aid=8061748&no_rooms=1&group_adults=2"},"vatolotolo":{"city":"Vatolotolo","count":"1","id":"-1196273","url":"https://www.booking.com/searchresults.en.html?city=-1196273&aid=8061748&no_rooms=1&group_adults=2"},"vatutandova":{"city":"Vatutandova","count":"1","id":"-1196480","url":"https://www.booking.com/searchresults.en.html?city=-1196480&aid=8061748&no_rooms=1&group_adults=2"},"vatuwangga":{"city":"Vatuwangga","count":"0","id":"-1196533","url":"https://www.booking.com/searchresults.en.html?city=-1196533&aid=8061748&no_rooms=1&group_adults=2"},"viseisei":{"city":"Viseisei","count":"1","id":"-1196721","url":"https://www.booking.com/searchresults.en.html?city=-1196721&aid=8061748&no_rooms=1&group_adults=2"},"vitawa":{"city":"Vitawa","count":"0","id":"-1196735","url":"https://www.booking.com/searchresults.en.html?city=-1196735&aid=8061748&no_rooms=1&group_adults=2"},"viwa":{"city":"Viwa","count":"1","id":"900053481","url":"https://www.booking.com/searchresults.en.html?city=900053481&aid=8061748&no_rooms=1&group_adults=2"},"vomo":{"city":"Vomo","count":"1","id":"900050424","url":"https://www.booking.com/searchresults.en.html?city=900050424&aid=8061748&no_rooms=1&group_adults=2"},"votua":{"city":"Votua","count":"0","id":"-1196815","url":"https://www.booking.com/searchresults.en.html?city=-1196815&aid=8061748&no_rooms=1&group_adults=2"},"voua":{"city":"Voua","count":"1","id":"-1196824","url":"https://www.booking.com/searchresults.en.html?city=-1196824&aid=8061748&no_rooms=1&group_adults=2"},"vuake":{"city":"Vuake","count":"1","id":"-1196833","url":"https://www.booking.com/searchresults.en.html?city=-1196833&aid=8061748&no_rooms=1&group_adults=2"},"vunaniu":{"city":"Vunaniu","count":"1","id":"-1196974","url":"https://www.booking.com/searchresults.en.html?city=-1196974&aid=8061748&no_rooms=1&group_adults=2"},"vunisea station":{"city":"Vunisea Station","count":"0","id":"-1197241","url":"https://www.booking.com/searchresults.en.html?city=-1197241&aid=8061748&no_rooms=1&group_adults=2"},"waiyevo":{"city":"Waiyevo","count":"7","id":"-1198917","url":"https://www.booking.com/searchresults.en.html?city=-1198917&aid=8061748&no_rooms=1&group_adults=2"},"wakaya island":{"city":"Wakaya Island","count":"0","id":"900054195","url":"https://www.booking.com/searchresults.en.html?city=900054195&aid=8061748&no_rooms=1&group_adults=2"},"wayasewa island":{"city":"Wayasewa Island","count":"2","id":"900051858","url":"https://www.booking.com/searchresults.en.html?city=900051858&aid=8061748&no_rooms=1&group_adults=2"},"yakuve island":{"city":"Yakuve Island","count":"1","id":"-1193465","url":"https://www.booking.com/searchresults.en.html?city=-1193465&aid=8061748&no_rooms=1&group_adults=2"},"yandua":{"city":"Yandua","count":"2","id":"-1199117","url":"https://www.booking.com/searchresults.en.html?city=-1199117&aid=8061748&no_rooms=1&group_adults=2"}}