{"acoua":{"city":"Acoua","count":"0","id":"335422","url":"https://www.booking.com/searchresults.en.html?city=335422&aid=8061748&no_rooms=1&group_adults=2"},"bandraboua":{"city":"Bandraboua","count":"0","id":"335346","url":"https://www.booking.com/searchresults.en.html?city=335346&aid=8061748&no_rooms=1&group_adults=2"},"bandrani":{"city":"Bandrani","count":"0","id":"337104","url":"https://www.booking.com/searchresults.en.html?city=337104&aid=8061748&no_rooms=1&group_adults=2"},"bandrele":{"city":"Bandrélé","count":"3","id":"337571","url":"https://www.booking.com/searchresults.en.html?city=337571&aid=8061748&no_rooms=1&group_adults=2"},"boueni":{"city":"Bouéni","count":"0","id":"337876","url":"https://www.booking.com/searchresults.en.html?city=337876&aid=8061748&no_rooms=1&group_adults=2"},"chiconi":{"city":"Chiconi","count":"0","id":"337086","url":"https://www.booking.com/searchresults.en.html?city=337086&aid=8061748&no_rooms=1&group_adults=2"},"chirongui":{"city":"Chirongui","count":"0","id":"337652","url":"https://www.booking.com/searchresults.en.html?city=337652&aid=8061748&no_rooms=1&group_adults=2"},"combani":{"city":"Combani","count":"0","id":"335791","url":"https://www.booking.com/searchresults.en.html?city=335791&aid=8061748&no_rooms=1&group_adults=2"},"dzaoudzi":{"city":"Dzaoudzi","count":"1","id":"336810","url":"https://www.booking.com/searchresults.en.html?city=336810&aid=8061748&no_rooms=1&group_adults=2"},"kangani":{"city":"Kangani","count":"1","id":"335962","url":"https://www.booking.com/searchresults.en.html?city=335962&aid=8061748&no_rooms=1&group_adults=2"},"kani be":{"city":"Kani Bé","count":"0","id":"337894","url":"https://www.booking.com/searchresults.en.html?city=337894&aid=8061748&no_rooms=1&group_adults=2"},"kani keli":{"city":"Kani Keli","count":"1","id":"337885","url":"https://www.booking.com/searchresults.en.html?city=337885&aid=8061748&no_rooms=1&group_adults=2"},"kaoueni":{"city":"Kaouéni","count":"0","id":"336731","url":"https://www.booking.com/searchresults.en.html?city=336731&aid=8061748&no_rooms=1&group_adults=2"},"kavani":{"city":"Kavani","count":"0","id":"336732","url":"https://www.booking.com/searchresults.en.html?city=336732&aid=8061748&no_rooms=1&group_adults=2"},"koungou":{"city":"Koungou","count":"13","id":"335974","url":"https://www.booking.com/searchresults.en.html?city=335974&aid=8061748&no_rooms=1&group_adults=2"},"labattoir":{"city":"Labattoir","count":"1","id":"336813","url":"https://www.booking.com/searchresults.en.html?city=336813&aid=8061748&no_rooms=1&group_adults=2"},"majikavo koropa":{"city":"Majikavo Koropa","count":"1","id":"336682","url":"https://www.booking.com/searchresults.en.html?city=336682&aid=8061748&no_rooms=1&group_adults=2"},"majikavo lamir":{"city":"Majikavo Lamir","count":"0","id":"336690","url":"https://www.booking.com/searchresults.en.html?city=336690&aid=8061748&no_rooms=1&group_adults=2"},"mamoudzou":{"city":"Mamoudzou","count":"12","id":"-2087895","url":"https://www.booking.com/searchresults.en.html?city=-2087895&aid=8061748&no_rooms=1&group_adults=2"},"mbouini":{"city":"Mbouini","count":"0","id":"337806","url":"https://www.booking.com/searchresults.en.html?city=337806&aid=8061748&no_rooms=1&group_adults=2"},"mitseni":{"city":"Mitséni","count":"0","id":"335799","url":"https://www.booking.com/searchresults.en.html?city=335799&aid=8061748&no_rooms=1&group_adults=2"},"mrowale":{"city":"Mrowalé","count":"0","id":"335790","url":"https://www.booking.com/searchresults.en.html?city=335790&aid=8061748&no_rooms=1&group_adults=2"},"mtsamboro":{"city":"Mtsamboro","count":"1","id":"335390","url":"https://www.booking.com/searchresults.en.html?city=335390&aid=8061748&no_rooms=1&group_adults=2"},"mtsamgamouji":{"city":"Mtsamgamouji","count":"0","id":"335465","url":"https://www.booking.com/searchresults.en.html?city=335465&aid=8061748&no_rooms=1&group_adults=2"},"mtsangadoua":{"city":"Mtsangadoua","count":"1","id":"335403","url":"https://www.booking.com/searchresults.en.html?city=335403&aid=8061748&no_rooms=1&group_adults=2"},"ongojou":{"city":"Ongojou","count":"0","id":"337072","url":"https://www.booking.com/searchresults.en.html?city=337072&aid=8061748&no_rooms=1&group_adults=2"},"ouangani":{"city":"Ouangani","count":"0","id":"337075","url":"https://www.booking.com/searchresults.en.html?city=337075&aid=8061748&no_rooms=1&group_adults=2"},"pamandzi":{"city":"Pamandzi","count":"2","id":"337047","url":"https://www.booking.com/searchresults.en.html?city=337047&aid=8061748&no_rooms=1&group_adults=2"},"sada":{"city":"Sada","count":"2","id":"337105","url":"https://www.booking.com/searchresults.en.html?city=337105&aid=8061748&no_rooms=1&group_adults=2"},"sohoa":{"city":"Sohoa","count":"1","id":"336801","url":"https://www.booking.com/searchresults.en.html?city=336801&aid=8061748&no_rooms=1&group_adults=2"},"sohoa keli":{"city":"Sohoa Kéli","count":"0","id":"336802","url":"https://www.booking.com/searchresults.en.html?city=336802&aid=8061748&no_rooms=1&group_adults=2"},"tsingoni":{"city":"Tsingoni","count":"1","id":"335783","url":"https://www.booking.com/searchresults.en.html?city=335783&aid=8061748&no_rooms=1&group_adults=2"},"tsoundzou 1":{"city":"Tsoundzou 1","count":"0","id":"336766","url":"https://www.booking.com/searchresults.en.html?city=336766&aid=8061748&no_rooms=1&group_adults=2"},"tsoundzou 2":{"city":"Tsoundzou 2","count":"0","id":"336777","url":"https://www.booking.com/searchresults.en.html?city=336777&aid=8061748&no_rooms=1&group_adults=2"}}